sensecraft/__init__.py
sensecraft/loss/__init__.py
sensecraft/loss/config.py
sensecraft/loss/convnext.py
sensecraft/loss/convnext_dinov3.py
sensecraft/loss/edge.py
sensecraft/loss/general.py
sensecraft/loss/gram_dinov3.py
sensecraft/loss/lpips.py
sensecraft/loss/sensecraft.py
sensecraft/loss/ssim.py
sensecraft/loss/video.py
sensecraft/loss/weights/v0.0/alex.pth
sensecraft/loss/weights/v0.0/squeeze.pth
sensecraft/loss/weights/v0.0/vgg.pth
sensecraft/loss/weights/v0.1/alex.pth
sensecraft/loss/weights/v0.1/squeeze.pth
sensecraft/loss/weights/v0.1/vgg.pth
sensecraft/metrics/__init__.py
sensecraft/metrics/image.py
sensecraft/modules/__init__.py
sensecraft/modules/lpips_pretrained_net.py
sensecraft/utils/__init__.py
sensecraft/utils/lpips.py
sensecraft-0.3.11.dist-info/licenses/LICENSE
sensecraft-0.3.11.dist-info/METADATA
sensecraft-0.3.11.dist-info/WHEEL
sensecraft-0.3.11.dist-info/top_level.txt
sensecraft-0.3.11.dist-info/RECORD
