Metadata-Version: 2.4
Name: sensecraft
Version: 0.3.11
Author-email: "Shih-Ying Yeh(KohakuBlueLeaf)" <apolloyeh0123@gmail.com>
License: Apache-2.0
Project-URL: Homepage, https://kblueleaf.net/SenseCraft
Requires-Python: >=3.10
License-File: LICENSE
Requires-Dist: torch
Requires-Dist: torchvision
Requires-Dist: numpy
Requires-Dist: pytorch-msssim
Provides-Extra: dev
Requires-Dist: pytest; extra == "dev"
Provides-Extra: dinov3
Requires-Dist: transformers>=4.56.0; extra == "dinov3"
Provides-Extra: full
Requires-Dist: transformers>=4.56.0; extra == "full"
Requires-Dist: scikit-image; extra == "full"
Dynamic: license-file
